myawesomelib/__init__.py
myawesomelib/myawesomecodes.py
myawesomelib-0.1.0.dist-info/METADATA
myawesomelib-0.1.0.dist-info/WHEEL
myawesomelib-0.1.0.dist-info/top_level.txt
myawesomelib-0.1.0.dist-info/RECORD
