Metadata-Version: 2.1
Name: myawesomelib
Version: 0.1.0
Summary: My first Python library
Home-page: UNKNOWN
Author: Me
Author-email: UNKNOWN
License: MIT
Platform: UNKNOWN
